odoo/addons/crm_timesheet/README.rst
odoo/addons/crm_timesheet/__init__.py
odoo/addons/crm_timesheet/__manifest__.py
odoo/addons/crm_timesheet/i18n/crm_timesheet.pot
odoo/addons/crm_timesheet/i18n/cs_CZ.po
odoo/addons/crm_timesheet/i18n/de.po
odoo/addons/crm_timesheet/i18n/es.po
odoo/addons/crm_timesheet/i18n/fr.po
odoo/addons/crm_timesheet/i18n/it.po
odoo/addons/crm_timesheet/models/__init__.py
odoo/addons/crm_timesheet/models/account_analytic_line.py
odoo/addons/crm_timesheet/models/crm_lead.py
odoo/addons/crm_timesheet/readme/CONTRIBUTORS.rst
odoo/addons/crm_timesheet/readme/DESCRIPTION.rst
odoo/addons/crm_timesheet/readme/ROADMAP.rst
odoo/addons/crm_timesheet/readme/USAGE.rst
odoo/addons/crm_timesheet/static/description/icon.png
odoo/addons/crm_timesheet/static/description/index.html
odoo/addons/crm_timesheet/tests/__init__.py
odoo/addons/crm_timesheet/tests/test_account_analytic_line.py
odoo/addons/crm_timesheet/views/crm_lead_view.xml
odoo/addons/crm_timesheet/views/hr_timesheet_view.xml
odoo11_addon_crm_timesheet-11.0.1.0.1.dist-info/METADATA
odoo11_addon_crm_timesheet-11.0.1.0.1.dist-info/WHEEL
odoo11_addon_crm_timesheet-11.0.1.0.1.dist-info/top_level.txt
odoo11_addon_crm_timesheet-11.0.1.0.1.dist-info/RECORD
